jwt_auth_validator/__init__.py
jwt_auth_validator/cache.py
jwt_auth_validator/config.py
jwt_auth_validator/decorators.py
jwt_auth_validator/jwt_utils.py
jwt_auth_validator/settings.py
jwt_auth_validator-0.1.0.dist-info/licenses/LICENSE
jwt_auth_validator-0.1.0.dist-info/METADATA
jwt_auth_validator-0.1.0.dist-info/WHEEL
jwt_auth_validator-0.1.0.dist-info/top_level.txt
jwt_auth_validator-0.1.0.dist-info/RECORD
