Metadata-Version: 2.4
Name: jwt-auth-validator
Version: 0.1.0
Summary: JWT validator with public key verification and permission check
Author: Mohammadreza Teheri
Author-email: mrtcode2@gmail.com
Classifier: Programming Language :: Python :: 3
Classifier: License :: OSI Approved :: MIT License
Requires-Python: >=3.7
License-File: LICENSE
Requires-Dist: pyjwt
Requires-Dist: requests
Requires-Dist: cryptography
Dynamic: author
Dynamic: author-email
Dynamic: classifier
Dynamic: description
Dynamic: description-content-type
Dynamic: license-file
Dynamic: requires-dist
Dynamic: requires-python
Dynamic: summary
